setup.py
ai_probability/Binomialdistribution.py
ai_probability/Gaussiandistribution.py
ai_probability/Generaldistribution.py
ai_probability/__init__.py
ai_probability.egg-info/PKG-INFO
ai_probability.egg-info/SOURCES.txt
ai_probability.egg-info/dependency_links.txt
ai_probability.egg-info/not-zip-safe
ai_probability.egg-info/top_level.txt