Metadata-Version: 1.0
Name: ai-probability
Version: 0.1
Summary: Gaussian distributions
Home-page: UNKNOWN
Author: Zeeshan Keerio
Author-email: UNKNOWN
License: UNKNOWN
Platform: UNKNOWN
